odoo/addons/delivery_purchase_multi_destination/README.rst
odoo/addons/delivery_purchase_multi_destination/__init__.py
odoo/addons/delivery_purchase_multi_destination/__manifest__.py
odoo/addons/delivery_purchase_multi_destination/i18n/delivery_purchase_multi_destination.pot
odoo/addons/delivery_purchase_multi_destination/i18n/it.po
odoo/addons/delivery_purchase_multi_destination/models/__init__.py
odoo/addons/delivery_purchase_multi_destination/models/delivery_carrier.py
odoo/addons/delivery_purchase_multi_destination/models/purchase_order.py
odoo/addons/delivery_purchase_multi_destination/readme/CONFIGURE.md
odoo/addons/delivery_purchase_multi_destination/readme/CONTRIBUTORS.md
odoo/addons/delivery_purchase_multi_destination/readme/DESCRIPTION.md
odoo/addons/delivery_purchase_multi_destination/readme/USAGE.md
odoo/addons/delivery_purchase_multi_destination/static/description/icon.png
odoo/addons/delivery_purchase_multi_destination/static/description/index.html
odoo/addons/delivery_purchase_multi_destination/tests/__init__.py
odoo/addons/delivery_purchase_multi_destination/tests/test_delivery_multi_destination.py
odoo_addon_delivery_purchase_multi_destination-17.0.1.0.0.4.dist-info/METADATA
odoo_addon_delivery_purchase_multi_destination-17.0.1.0.0.4.dist-info/WHEEL
odoo_addon_delivery_purchase_multi_destination-17.0.1.0.0.4.dist-info/top_level.txt
odoo_addon_delivery_purchase_multi_destination-17.0.1.0.0.4.dist-info/RECORD
