Metadata-Version: 2.1
Name: odoo-addon-delivery_purchase_multi_destination
Version: 17.0.1.0.0.4
Requires-Python: >=3.10
Requires-Dist: odoo-addon-delivery_multi_destination>=17.0dev,<17.1dev
Requires-Dist: odoo-addon-delivery_purchase>=17.0dev,<17.1dev
Requires-Dist: odoo>=17.0a,<17.1dev
Summary: Multiple origins for delivery costs in purchases
Home-page: https://github.com/OCA/delivery-carrier
License: AGPL-3
Author: Tecnativa, Odoo Community Association (OCA)
Author-email: support@odoo-community.org
Classifier: Programming Language :: Python
Classifier: Framework :: Odoo
Classifier: Framework :: Odoo :: 17.0
Classifier: License :: OSI Approved :: GNU Affero General Public License v3
